Genie/__init__.py
Genie/main.py
Genie/core/__init__.py
Genie/core/evolution.py
Genie/utils/__init__.py
Genie/utils/codon_utils.py
Genie/utils/parser.py
Genie/utils/pca_utils.py
Genie/utils/stats.py
Genie_aa/__init__.py
Genie_aa/main.py
Genie_aa/sampling/__init__.py
Genie_aa/sampling/sampling.py
Genie_aa/utils/__init__.py
Genie_aa/utils/parser.py
Genie_aa/utils/stats.py
genie_dca-2.0.0.dist-info/licenses/LICENSE
scripts/__init__.py
scripts/reconstruct_at_timesteps.py
scripts/reconstruct_chains.py
genie_dca-2.0.0.dist-info/METADATA
genie_dca-2.0.0.dist-info/WHEEL
genie_dca-2.0.0.dist-info/entry_points.txt
genie_dca-2.0.0.dist-info/top_level.txt
genie_dca-2.0.0.dist-info/RECORD
