Metadata-Version: 2.4
Name: genie-dca
Version: 2.0.0
Summary: GPU-Accelerated MCMC Sampling for Protein Sequences with Codon-Level Mutations
Author-email: Roberto Netti <roberto.netti@example.com>
License-Expression: MIT
Project-URL: Homepage, https://github.com/spqb/Genie.py
Project-URL: Documentation, https://github.com/spqb/Genie.py#readme
Project-URL: Repository, https://github.com/spqb/Genie.py
Project-URL: Issues, https://github.com/spqb/Genie.py/issues
Keywords: bioinformatics,protein,MCMC,DCA,GPU,codon,evolution
Classifier: Development Status :: 4 - Beta
Classifier: Intended Audience :: Science/Research
Classifier: Topic :: Scientific/Engineering :: Bio-Informatics
Classifier: Programming Language :: Python :: 3
Classifier: Programming Language :: Python :: 3.8
Classifier: Programming Language :: Python :: 3.9
Classifier: Programming Language :: Python :: 3.10
Classifier: Programming Language :: Python :: 3.11
Classifier: Operating System :: OS Independent
Requires-Python: >=3.8
License-File: LICENSE
Requires-Dist: adabmDCA>=0.7
Requires-Dist: torch>=2.0.0
Requires-Dist: numpy>=1.20.0
Requires-Dist: pandas>=1.3.0
Requires-Dist: matplotlib>=3.0.0
Requires-Dist: scikit-learn>=1.0.0
Provides-Extra: dev
Requires-Dist: pytest>=7.0; extra == "dev"
Requires-Dist: black; extra == "dev"
Requires-Dist: flake8; extra == "dev"
Requires-Dist: mypy; extra == "dev"
Provides-Extra: docs
Requires-Dist: sphinx; extra == "docs"
Requires-Dist: sphinx-rtd-theme; extra == "docs"
Dynamic: license-file
